MANIFEST.in
README.rst
setup.py
soup_helpers/__init__.py
soup_helpers/objects.py
soup_helpers.egg-info/PKG-INFO
soup_helpers.egg-info/SOURCES.txt
soup_helpers.egg-info/dependency_links.txt
soup_helpers.egg-info/not-zip-safe
soup_helpers.egg-info/requires.txt
soup_helpers.egg-info/top_level.txt