Metadata-Version: 1.0
Name: soup-helpers
Version: 0.0.4
Summary: A simple set of BeautifulSoup4 unit test helpers
Home-page: https://bitbucket.org/bigmassa/soup_helpers
Author: Stuart George
Author-email: stuart.bigmassa@gmail.com
License: MIT
Platform: UNKNOWN
